{"id":"68f8fc8f-02fc-457c-8da7-6ed2d6bd7bdf","timestamp":1777453480074,"matcher":{"static":{"/cases":{"redirect":"/kennisbank/klantcases"},"/cases/azure":{"redirect":"/kennisbank/klantcases/azure"},"/cases/front-end":{"redirect":"/kennisbank/klantcases/front-end"},"/cases/dotnet":{"redirect":"/kennisbank/klantcases/dotnet"},"/cases/microsoft-365":{"redirect":"/kennisbank/klantcases/microsoft-365"},"/updates":{"redirect":"/kennisbank"},"/nieuws":{"redirect":"/kennisbank/nieuws"},"/blogs":{"redirect":"/kennisbank/blogs"},"/events":{"redirect":"/kennisbank/events"},"/klantcases":{"redirect":"/kennisbank/klantcases"}},"wildcard":{"/updates/nieuws":{"redirect":"/kennisbank/nieuws"},"/updates/blogs":{"redirect":"/kennisbank/blogs"},"/updates/events":{"redirect":"/kennisbank/events"},"/events/2021":{"redirect":"/kennisbank/events"},"/events/2022":{"redirect":"/kennisbank/events"},"/events/2023":{"redirect":"/kennisbank/events"}},"dynamic":{}},"prerendered":[]}